pynereus/__init__.py
pynereus/calc_cross_section.py
pynereus/constants.py
pynereus/nereus_gui.py
pynereus/plots.py
pynereus/reactions.py
pynereus/reactivities.py
pynereus/response.py
pynereus/rw_for.py
pynereus/dress_client/fi_codes.py
pynereus/dress_client/nspectrum.py
pynereus/los/los.py
pynereus/nresp/crossSections.py
pynereus/nresp/en2light.py
pynereus/nresp/nresp.py
pynereus-0.0.5.dist-info/LICENSE
pynereus-0.0.5.dist-info/METADATA
pynereus-0.0.5.dist-info/WHEEL
pynereus-0.0.5.dist-info/top_level.txt
pynereus-0.0.5.dist-info/RECORD
